catmux/__init__.py
catmux/catmux_create_session.py
catmux/exceptions.py
catmux/prefix.py
catmux/session.py
catmux/split.py
catmux/tmux_wrapper.py
catmux/window.py
catmux/resources/__init__.py
catmux/resources/example_session.yaml
catmux/resources/readme_tmux.txt
catmux/resources/tmux_default.conf
catmux-0.3.6.data/scripts/catmux
catmux-0.3.6.dist-info/LICENSE
catmux-0.3.6.dist-info/METADATA
catmux-0.3.6.dist-info/WHEEL
catmux-0.3.6.dist-info/entry_points.txt
catmux-0.3.6.dist-info/top_level.txt
catmux-0.3.6.dist-info/RECORD
