Metadata-Version: 2.1
Name: catmux
Version: 0.3.6
Summary: A tmux orchestration package.
Home-page: https://github.com/fmauch/catmux
Author: Felix Exner
Author-email: felix_mauch@web.de
License: MIT
Classifier: Programming Language :: Python :: 3
Classifier: License :: OSI Approved :: MIT License
Classifier: Operating System :: OS Independent
Requires-Python: >=3.7
License-File: LICENSE
Requires-Dist: pyyaml
